lazzy_orm/__init__.py
lazzy_orm/config/__init__.py
lazzy_orm/config/connector.py
lazzy_orm/config/date_parser.py
lazzy_orm/lazzy_fetch/__init__.py
lazzy_orm/lazzy_fetch/lazzy_fetch.py
lazzy_orm/lazzy_insert/__init__.py
lazzy_orm/lazzy_insert/lazzy_insert.py
lazzy_orm/logger/__init__.py
lazzy_orm/logger/logger.py
LazzyORM-0.2.2.dist-info/LICENSE
LazzyORM-0.2.2.dist-info/METADATA
LazzyORM-0.2.2.dist-info/WHEEL
LazzyORM-0.2.2.dist-info/entry_points.txt
LazzyORM-0.2.2.dist-info/top_level.txt
LazzyORM-0.2.2.dist-info/RECORD
